mdnsbridge/__init__.py
mdnsbridge/mdnsbridge.py
mdnsbridge/mdnsbridgeclient.py
mdnsbridge/mdnsbridgeservice.py
usr/bin/nmos-mdnsbridge
mdnsbridge-0.9.4.dist-info/LICENSE.md
mdnsbridge-0.9.4.dist-info/METADATA
mdnsbridge-0.9.4.dist-info/WHEEL
mdnsbridge-0.9.4.dist-info/top_level.txt
mdnsbridge-0.9.4.dist-info/RECORD
