Metadata-Version: 1.0
Name: mdnsbridge
Version: 0.9.4
Summary: An API providing a DNS-SD/HTTP bridge for AMWA NMOS service types
Home-page: https://github.com/bbc/nmos-mdns-bridge
Author: Peter Brightwell
Author-email: peter.brightwell@bbc.co.uk
License: Apache 2
Platform: UNKNOWN
